traceblame/__init__.py
traceblame/main.py
traceblame-0.0.7.dist-info/LICENSE
traceblame-0.0.7.dist-info/METADATA
traceblame-0.0.7.dist-info/WHEEL
traceblame-0.0.7.dist-info/top_level.txt
traceblame-0.0.7.dist-info/RECORD
