Metadata-Version: 2.1
Name: traceblame
Version: 0.0.7
Summary: Tool to extend locals variables in stacktrace by git blame information for python projects
Home-page: https://github.com/ncopiy/traceblame
Author: ncopiy
Author-email: ncopiy@yandex.com
Classifier: Programming Language :: Python :: 3
Classifier: License :: OSI Approved :: MIT License
Requires-Python: >=3.7
License-File: LICENSE
Requires-Dist: GitPython (==3.1.30)
